sphinxcontrib/spelling/__init__.py
sphinxcontrib/spelling/asset.py
sphinxcontrib/spelling/builder.py
sphinxcontrib/spelling/checker.py
sphinxcontrib/spelling/directive.py
sphinxcontrib/spelling/domain.py
sphinxcontrib/spelling/filters.py
sphinxcontrib/spelling/role.py
sphinxcontrib/spelling/version.py
sphinxcontrib_spelling-8.0.0.dist-info/AUTHORS
sphinxcontrib_spelling-8.0.0.dist-info/LICENSE
sphinxcontrib_spelling-8.0.0.dist-info/METADATA
sphinxcontrib_spelling-8.0.0.dist-info/WHEEL
sphinxcontrib_spelling-8.0.0.dist-info/entry_points.txt
sphinxcontrib_spelling-8.0.0.dist-info/pbr.json
sphinxcontrib_spelling-8.0.0.dist-info/top_level.txt
sphinxcontrib_spelling-8.0.0.dist-info/RECORD
