Metadata-Version: 2.1
Name: sphinxcontrib-spelling
Version: 8.0.0
Summary: Sphinx spelling extension
Author-email: Doug Hellmann <doug@doughellmann.com>
Project-URL: homepage, https://sphinxcontrib-spelling.readthedocs.io/en/latest/
Project-URL: repository, https://github.com/sphinx-contrib/spelling
Classifier: Development Status :: 5 - Production/Stable
Classifier: Environment :: Console
Classifier: Environment :: Web Environment
Classifier: Framework :: Sphinx :: Extension
Classifier: Intended Audience :: Developers
Classifier: License :: OSI Approved :: BSD License
Classifier: Operating System :: OS Independent
Classifier: Programming Language :: Python
Classifier: Programming Language :: Python :: 3
Classifier: Programming Language :: Python :: 3 :: Only
Classifier: Programming Language :: Python :: 3.7
Classifier: Programming Language :: Python :: 3.8
Classifier: Programming Language :: Python :: 3.9
Classifier: Programming Language :: Python :: 3.10
Classifier: Programming Language :: Python :: 3.11
Classifier: Programming Language :: Python :: Implementation :: CPython
Classifier: Topic :: Documentation
Classifier: Topic :: Utilities
Requires-Python: >=3.7
Provides-Extra: test
License-File: LICENSE
License-File: AUTHORS
